sinlib/__init__.py
sinlib/romanize.py
sinlib/spellcheck.py
sinlib/tokenizer.py
sinlib/transliterate.py
sinlib/utils/__init__.py
sinlib/utils/chars.py
sinlib/utils/dataset_utils.py
sinlib/utils/model_utils.py
sinlib/utils/preprocessing.py
sinlib/utils/models/__init__.py
sinlib/utils/models/transliterator-checkpoint.pth
sinlib/utils/models/transliterator_model.py
sinlib-0.1.10.dist-info/METADATA
sinlib-0.1.10.dist-info/WHEEL
sinlib-0.1.10.dist-info/licenses/LICENSE
sinlib-0.1.10.dist-info/RECORD
