Metadata-Version: 2.4
Name: sinlib
Version: 0.1.10
Summary: Sinhala NLP Toolkit
Project-URL: Code, https://github.com/Ransaka/sinlib
Project-URL: Docs, https://github.com/Ransaka/sinlib
Author-email: Ransaka <ransaka.ravihara@gmail.com>
License: MIT License
License-File: LICENSE
Keywords: NLP,Sinhala,python
Classifier: License :: OSI Approved :: MIT License
Classifier: Programming Language :: Python :: 3.9
Classifier: Programming Language :: Python :: 3.10
Classifier: Programming Language :: Python :: 3.11
Classifier: Topic :: Scientific/Engineering :: Artificial Intelligence
Requires-Python: <=3.12,>=3.9.7
Requires-Dist: huggingface-hub
Requires-Dist: numpy>=1.24.0
Requires-Dist: tqdm>=4.64.1
Requires-Dist: transformers>=4.31.0
